pyenvcustomize/__init__.py
pyenvcustomize-0.0.2.dist-info/METADATA
pyenvcustomize-0.0.2.dist-info/WHEEL
pyenvcustomize-0.0.2.dist-info/top_level.txt
pyenvcustomize-0.0.2.dist-info/RECORD
