Metadata-Version: 2.1
Name: pyenvcustomize
Version: 0.0.2
Summary: Automatically create or update sitecustomize.py in the Python environment
Home-page: https://github.com/jaygarage/pyenvcustomize
Author: Jay
Classifier: Programming Language :: Python :: 3
Classifier: License :: OSI Approved :: MIT License
Classifier: Operating System :: OS Independent
